{
  "id": "41b21700-bd5d-4638-b933-69b3196f8f13",
  "prevId": "7af5e71c-3b15-4e89-9f90-f69babb4b9bd",
  "version": "7",
  "dialect": "postgresql",
  "tables": {
    "public.error_logs": {
      "name": "error_logs",
      "schema": "",
      "columns": {
        "id": {
          "name": "id",
          "type": "uuid",
          "primaryKey": true,
          "notNull": true,
          "default": "gen_random_uuid()"
        },
        "status": {
          "name": "status",
          "type": "integer",
          "primaryKey": false,
          "notNull": true
        },
        "message": {
          "name": "message",
          "type": "text",
          "primaryKey": false,
          "notNull": true
        },
        "stack": {
          "name": "stack",
          "type": "text",
          "primaryKey": false,
          "notNull": false
        },
        "path": {
          "name": "path",
          "type": "text",
          "primaryKey": false,
          "notNull": true
        },
        "method": {
          "name": "method",
          "type": "text",
          "primaryKey": false,
          "notNull": true
        },
        "created_at": {
          "name": "created_at",
          "type": "timestamp with time zone",
          "primaryKey": false,
          "notNull": true,
          "default": "now()"
        }
      },
      "indexes": {},
      "foreignKeys": {},
      "compositePrimaryKeys": {},
      "uniqueConstraints": {},
      "policies": {},
      "checkConstraints": {},
      "isRLSEnabled": false
    },
    "public.cities": {
      "name": "cities",
      "schema": "",
      "columns": {
        "id": {
          "name": "id",
          "type": "integer",
          "primaryKey": true,
          "notNull": true
        },
        "name": {
          "name": "name",
          "type": "varchar(150)",
          "primaryKey": false,
          "notNull": true
        },
        "state_id": {
          "name": "state_id",
          "type": "integer",
          "primaryKey": false,
          "notNull": true
        }
      },
      "indexes": {},
      "foreignKeys": {
        "cities_state_id_states_id_fk": {
          "name": "cities_state_id_states_id_fk",
          "tableFrom": "cities",
          "tableTo": "states",
          "columnsFrom": [
            "state_id"
          ],
          "columnsTo": [
            "id"
          ],
          "onDelete": "no action",
          "onUpdate": "no action"
        }
      },
      "compositePrimaryKeys": {},
      "uniqueConstraints": {
        "unique_city_per_state": {
          "name": "unique_city_per_state",
          "nullsNotDistinct": false,
          "columns": [
            "name",
            "state_id"
          ]
        }
      },
      "policies": {},
      "checkConstraints": {},
      "isRLSEnabled": false
    },
    "public.states": {
      "name": "states",
      "schema": "",
      "columns": {
        "id": {
          "name": "id",
          "type": "integer",
          "primaryKey": true,
          "notNull": true
        },
        "name": {
          "name": "name",
          "type": "varchar(50)",
          "primaryKey": false,
          "notNull": true
        },
        "abbreviation": {
          "name": "abbreviation",
          "type": "char(2)",
          "primaryKey": false,
          "notNull": true
        }
      },
      "indexes": {},
      "foreignKeys": {},
      "compositePrimaryKeys": {},
      "uniqueConstraints": {
        "states_name_unique": {
          "name": "states_name_unique",
          "nullsNotDistinct": false,
          "columns": [
            "name"
          ]
        },
        "states_abbreviation_unique": {
          "name": "states_abbreviation_unique",
          "nullsNotDistinct": false,
          "columns": [
            "abbreviation"
          ]
        }
      },
      "policies": {},
      "checkConstraints": {},
      "isRLSEnabled": false
    }
  },
  "enums": {},
  "schemas": {},
  "sequences": {},
  "roles": {},
  "policies": {},
  "views": {},
  "_meta": {
    "columns": {},
    "schemas": {},
    "tables": {}
  }
}